{
  "miniprogramRoot": "dist/",
  "cloudfunctionRoot": "cloudfunctions/",
  "projectname": "班级助手2.0",
  "description": "班级助手微信小程序",
  "appid": "wx6c1ad09f87364a80",
  "setting": {
    "urlCheck": true,
    "es6": true,
    "enhance": true,
    "compileHotReLoad": false,
    "postcss": true,
    "preloadBackgroundData": false,
    "minified": true,
    "newFeature": true,
    "autoAudits": false,
    "coverView": true,
    "showShadowRootInWxmlPanel": false,
    "scopeDataCheck": false,
    "useCompilerModule": false,
    "compileWorklet": false,
    "uglifyFileName": false,
    "uploadWithSourceMap": true,
    "packNpmManually": false,
    "packNpmRelationList": [],
    "minifyWXSS": true,
    "minifyWXML": true,
    "localPlugins": false,
    "disableUseStrict": false,
    "useCompilerPlugins": false,
    "condition": false,
    "swc": true,
    "disableSWC": false,
    "babelSetting": {
      "ignore": [],
      "disablePlugins": [],
      "outputPath": ""
    }
  },
  "compileType": "miniprogram",
  "simulatorType": "wechat",
  "simulatorPluginLibVersion": {},
  "condition": {},
  "packOptions": {
    "ignore": [],
    "include": []
  },
  "editorSetting": {},
  "libVersion": "3.16.2"
}